mantle.py
terra_mantle-0.1.6.dist-info/LICENSE
terra_mantle-0.1.6.dist-info/METADATA
terra_mantle-0.1.6.dist-info/WHEEL
terra_mantle-0.1.6.dist-info/top_level.txt
terra_mantle-0.1.6.dist-info/RECORD
