Metadata-Version: 2.1
Name: terra-mantle
Version: 0.1.6
Summary: Terra mantle client
Home-page: https://github.com/Anchor-Protocol/mantle-client-python
Author: Ian Lee
Author-email: ian@terra.money
License: Apache-2.0
Platform: UNKNOWN
Requires-Python: >=3.5
Requires-Dist: gql (>=3.0.0a6)
Requires-Dist: graphql-core (>=3.1.5)
